README.rst
mdns-publish-cname
setup.py
mdns_publisher.egg-info/PKG-INFO
mdns_publisher.egg-info/SOURCES.txt
mdns_publisher.egg-info/dependency_links.txt
mdns_publisher.egg-info/not-zip-safe
mdns_publisher.egg-info/requires.txt
mdns_publisher.egg-info/top_level.txt
mpublisher/__init__.py
mpublisher/cname_service.py
mpublisher/mpublisher.py
mpublisher/_avahi/__init__.py