Metadata-Version: 1.1
Name: mdns-publisher
Version: 0.9.2
Summary: Publish CNAMEs pointing to the local host over Avahi/mDNS
Home-page: https://github.com/carlosefr/mdns-publisher
Author: Carlos Rodrigues
Author-email: cefrodrigues@gmail.com
License: MIT
Keywords: Avahi mDNS CNAME
Platform: UNKNOWN
Classifier: Development Status :: 5 - Production/Stable
Classifier: Environment :: Console
Classifier: License :: OSI Approved :: MIT License
Classifier: Programming Language :: Python :: 2
Classifier: Programming Language :: Python :: 3
Classifier: Topic :: Software Development :: Libraries
Classifier: Topic :: Utilities
Classifier: Intended Audience :: System Administrators
Classifier: Intended Audience :: Developers
